.cvsignore
README.txt
setup.py
src/.cvsignore
src/userschema/CHANGES.txt
src/userschema/README.txt
src/userschema/__init__.py
src/userschema/configure.zcml
src/userschema/csv-schema.txt
src/userschema/etree-schema.txt
src/userschema/etree.py
src/userschema/html-form-schema.txt
src/userschema/interfaces.py
src/userschema/meta.zcml
src/userschema/schema.py
src/userschema/version.txt
src/userschema/zcml.py
src/userschema.egg-info/PKG-INFO
src/userschema.egg-info/SOURCES.txt
src/userschema.egg-info/dependency_links.txt
src/userschema.egg-info/not-zip-safe
src/userschema.egg-info/requires.txt
src/userschema.egg-info/top_level.txt
src/userschema/tests/__init__.py
src/userschema/tests/test_etree.py
src/userschema/tests/test_schema.py
