Metadata-Version: 1.0
Name: userschema
Version: 0.8.1
Summary: Schema defined by business users
Home-page: http://agendaless.com/Members/tseaver/software/userschema
Author: Tres Seaver, Agendaless Consulting, Inc.
Author-email: tseaver@agendaless.com
License: ZPL 2.1
Platform: UNKNOWN
